GA_kit/Version.py
GA_kit/__init__.py
GA_kit/deceptive.py
GA_kit/ecga.py
GA_kit/hboa.py
GA_kit/sga.py
GA_kit-0.2.1.dist-info/LICENSE
GA_kit-0.2.1.dist-info/METADATA
GA_kit-0.2.1.dist-info/WHEEL
GA_kit-0.2.1.dist-info/entry_points.txt
GA_kit-0.2.1.dist-info/top_level.txt
GA_kit-0.2.1.dist-info/RECORD
