Metadata-Version: 2.1
Name: GA-kit
Version: 0.2.1
Summary: Advanced Genetic Algorithm Toolkit
Home-page: https://github.com/schlatterbeck/GA_kit
Author: Ralf Schlatterbeck
Author-email: Ralf Schlatterbeck <rsc@runtux.com>
License: BSD License
Project-URL: Homepage, https://github.com/schlatterbeck/GA_kit
Project-URL: Bug Tracker, https://github.com/schlatterbeck/GA_kit/issues
Platform: Any
Classifier: Development Status :: 3 - Alpha
Classifier: Environment :: Console
Classifier: Intended Audience :: Developers
Classifier: Intended Audience :: Education
Classifier: Intended Audience :: End Users/Desktop
Classifier: License :: OSI Approved :: BSD License
Classifier: Operating System :: OS Independent
Classifier: Programming Language :: Python
Classifier: Topic :: Education
Classifier: Programming Language :: Python :: 3.7
Classifier: Programming Language :: Python :: 3.8
Classifier: Programming Language :: Python :: 3.9
Classifier: Programming Language :: Python :: 3.10
Classifier: Programming Language :: Python :: 3.11
Requires-Python: >=3.7
License-File: LICENSE
Requires-Dist: pgapy
Requires-Dist: rsclib
